_examples/__init__.py
examples/__init__.py
pyexlatex/__init__.py
pyexlatex/df.py
pyexlatex/equations.py
pyexlatex/exc.py
pyexlatex/typing.py
pyexlatex/constants/__init__.py
pyexlatex/constants/flags.py
pyexlatex/figure/__init__.py
pyexlatex/figure/packages.py
pyexlatex/figure/pdf.py
pyexlatex/figure/models/__init__.py
pyexlatex/figure/models/figure.py
pyexlatex/figure/models/graphic.py
pyexlatex/figure/models/inlinegraphic.py
pyexlatex/figure/models/subfigure.py
pyexlatex/graphics/__init__.py
pyexlatex/graphics/arrow.py
pyexlatex/graphics/modified_picture.py
pyexlatex/graphics/rectangle.py
pyexlatex/graphics/shape.py
pyexlatex/graphics/flowcharts/__init__.py
pyexlatex/graphics/flowcharts/linear.py
pyexlatex/graphics/tikz/__init__.py
pyexlatex/graphics/tikz/item.py
pyexlatex/graphics/tikz/library.py
pyexlatex/graphics/tikz/path.py
pyexlatex/graphics/tikz/picture.py
pyexlatex/graphics/tikz/scope.py
pyexlatex/graphics/tikz/node/__init__.py
pyexlatex/graphics/tikz/node/node.py
pyexlatex/graphics/tikz/node/position/__init__.py
pyexlatex/graphics/tikz/node/position/directions.py
pyexlatex/graphics/tikz/node/position/position.py
pyexlatex/layouts/__init__.py
pyexlatex/layouts/base.py
pyexlatex/layouts/grid.py
pyexlatex/layouts/multicol.py
pyexlatex/layouts/spaced.py
pyexlatex/letter/__init__.py
pyexlatex/letter/closing.py
pyexlatex/letter/enclosures.py
pyexlatex/letter/letter.py
pyexlatex/letter/letterdocument.py
pyexlatex/letter/opening.py
pyexlatex/letter/ps.py
pyexlatex/letter/signature.py
pyexlatex/logic/__init__.py
pyexlatex/logic/builder.py
pyexlatex/logic/tools.py
pyexlatex/logic/type_check.py
pyexlatex/logic/extract/__init__.py
pyexlatex/logic/extract/by_attr.py
pyexlatex/logic/extract/by_type.py
pyexlatex/logic/extract/docitems.py
pyexlatex/logic/extract/get.py
pyexlatex/logic/extract/tools.py
pyexlatex/logic/format/__init__.py
pyexlatex/logic/format/and_join.py
pyexlatex/logic/format/contents.py
pyexlatex/logic/format/eq.py
pyexlatex/logic/format/sizing.py
pyexlatex-0.14.0.dist-info/LICENSE.md
pyexlatex-0.14.0.dist-info/METADATA
pyexlatex-0.14.0.dist-info/WHEEL
pyexlatex-0.14.0.dist-info/entry_points.txt
pyexlatex-0.14.0.dist-info/top_level.txt
pyexlatex-0.14.0.dist-info/RECORD
