Metadata-Version: 2.1
Name: pyexlatex
Version: 0.14.0
Summary: Python Extends LaTeX - A High-Level Python API for Creating Latex Documents
Home-page: https://github.com/nickderobertis/py-ex-latex
Author: Nick DeRobertis
Author-email: whoopnip@gmail.com
License: MIT
Project-URL: Code, https://github.com/nickderobertis/py-ex-latex
Project-URL: Documentation, https://nickderobertis.github.io/py-ex-latex
Platform: UNKNOWN
Classifier: Development Status :: 3 - Alpha
Classifier: Intended Audience :: Developers
Classifier: Programming Language :: Python :: 3.6
Classifier: Programming Language :: Python :: 3.7
Requires-Dist: mixins
Requires-Dist: pandas
Requires-Dist: tempdir
Requires-Dist: data
Requires-Dist: latex
Requires-Dist: future
Requires-Dist: sympy
Requires-Dist: shutilwhich
Requires-Dist: bibtexparser
Requires-Dist: Jinja2
Requires-Dist: matplotlib
Requires-Dist: typing-extensions
